{
  "birds": 0,
  "elongation": 0.4793601464603855,
  "filthiness": 0.42278732374556344,
  "fortification": 0.5983272352193407,
  "forwardness": 0.5742109647514907,
  "grandiosity": 0.7557407515388677,
  "hype": 0,
  "id": "2a1a52b3-9759-44aa-ba49-b1437396d895",
  "inconvenience": 0.3341721389208974,
  "luxuriousness": 0,
  "mainColor": "#bf0043",
  "model": 8,
  "mods": [
    "FIRE_INSURANCE",
    "SOLAR_PANELS",
    "SECRET_BASE",
    "GRIND_RAIL",
    "SWEETENER"
  ],
  "mysticism": 0.4493541480949242,
  "name": "Yellowstone National (Ball)Park",
  "nickname": "Yellowstone",
  "obtuseness": 0.62670850403186,
  "ominousness": 0.49897353685967183,
  "renoCost": -1,
  "renoDiscard": [
    "psychoacoustics_mod",
    "solar_panels_mod",
    "peanut_mister_mod",
    "peanuts_plus",
    "fire_insurance_mod",
    "viscosity_minus",
    "solar_eclipse_plus",
    "coffee_threes_plus",
    "forwardness_minus",
    "secret_base_mod",
    "soundsystem_mod",
    "forwardness_minus",
    "grind_rail_mod",
    "birds_plus",
    "big_bucket_mod",
    "mysticism_minus",
    "blooddrain_plus",
    "elongation_minus",
    "salmon_cannons_mod",
    "sweetener_mod",
    "inconvenience_minus",
    "reverb_plus",
    "coffee_two_plus",
    "mysticism_plus",
    "coffee_threes_plus",
    "sun_two_plus",
    "black_hole_plus"
  ],
  "renoHand": [
    "fax_machine_mod",
    "flooding_plus",
    "ominousness_minus",
    "mysticism_plus",
    "obtuseness_plus",
    "reverb_plus",
    "echo_chamber_mod",
    "big_bucket_mod",
    "peanut_mister_mod"
  ],
  "renoLog": {
    "fire_insurance_mod": 1,
    "grind_rail_mod": 1,
    "secret_base_mod": 1,
    "solar_panels_mod": 1,
    "sweetener_mod": 1
  },
  "secondaryColor": "#f57aa5",
  "state": {
    "solarPanels": true
  },
  "teamId": "7966eb04-efcc-499b-8f03-d13916330531",
  "tertiaryColor": "#ffdbe7",
  "viscosity": 0.4830007638090093,
  "weather": {
    "1": 1,
    "11": 1
  }
}