{
  "anticapitalism": 0.6265214872400635,
  "armor": "",
  "baseThirst": 0.874443693753239,
  "baserunningRating": 0.4937520434745582,
  "bat": "",
  "blood": 12,
  "buoyancy": 0.1964481417980246,
  "chasiness": 0.9915818763415908,
  "cinnamon": 0.8884984076741755,
  "coffee": 12,
  "coldness": 0.3351675576768256,
  "continuation": 0.3228988787807904,
  "deceased": false,
  "defenseRating": 0.6446719146807466,
  "divinity": 0.6062779160940575,
  "eDensity": 26.09093314489631,
  "evolution": 0,
  "fate": 20,
  "gameAttr": [],
  "groundFriction": 1.0771585550445129,
  "hitStreak": 0,
  "hittingRating": 0.7622588518437934,
  "id": "3d293d6c-3a20-43ab-a895-2b7f1f28779f",
  "indulgence": 0.3009841971755411,
  "laserlikeness": 0.39327240027002375,
  "leagueTeamId": "d9f89a8a-c563-493e-9d64-78e4f9a55d4a",
  "martyrdom": 0.9373631233756954,
  "moxie": 0.885296915746553,
  "musclitude": 0.9294241582295536,
  "name": "Slosh Truk",
  "omniscience": 0.8405029452704454,
  "overpowerment": 0.721849507937297,
  "patheticism": 0.001,
  "peanutAllergy": false,
  "permAttr": [],
  "pitchingRating": 0.6631224159159322,
  "pressurization": 0.18554214161819815,
  "ritual": "Mind reading",
  "ruthlessness": 0.9211893145345308,
  "seasAttr": [],
  "shakespearianism": 0.4577783834117502,
  "soul": 5,
  "state": {},
  "suppression": 0.4861649603936998,
  "tenaciousness": 0.392085617653385,
  "thwackability": 0.794890511373957,
  "totalFingers": 10,
  "tournamentTeamId": null,
  "tragicness": 0.001,
  "unthwackability": 0.6394110687600765,
  "watchfulness": 0.18377340024730676,
  "weekAttr": []
}