{
  "anticapitalism": 0.7313702192801721,
  "baseThirst": 0.8257167355591326,
  "baserunningRating": 0.9615710005077754,
  "blood": 6,
  "buoyancy": 1.237156975406667,
  "chasiness": 0.3568833043279192,
  "cinnamon": 1.2497750051020056,
  "coffee": 13,
  "coldness": 0.4799619677162234,
  "continuation": 0.5493344878062216,
  "deceased": true,
  "defenseRating": 0.5947005891654857,
  "divinity": 0.5231301907824045,
  "eDensity": 30.40460021706251,
  "evolution": 0,
  "fate": 83,
  "gameAttr": [],
  "groundFriction": 1.122962185159836,
  "hitStreak": 0,
  "hittingRating": 0.6405568526774289,
  "id": "4e6ad1a1-7c71-49de-8bd5-c286712faf9e",
  "indulgence": 0.6197407361325453,
  "itemAttr": [],
  "items": [],
  "laserlikeness": 1.1644318845957016,
  "leagueTeamId": "adc5b394-8f76-416d-9ce9-813706877b84",
  "martyrdom": 0.7988634820184606,
  "moxie": 1.0371650670870405,
  "musclitude": 1.1218704187425168,
  "name": "Sutton Picklestein",
  "omniscience": 0.4685598413806424,
  "overpowerment": 0.3681619647561414,
  "patheticism": 0.001,
  "peanutAllergy": true,
  "permAttr": [
    "EGO1"
  ],
  "pitchingRating": 0.36097158865823975,
  "pressurization": 0.04476617328396637,
  "ritual": "Reassembling",
  "ruthlessness": 0.4241099978243542,
  "seasAttr": [],
  "shakespearianism": 0.42006559896886914,
  "soul": 3,
  "state": {},
  "suppression": 0.41007432853053527,
  "tenaciousness": 0.3657867007732458,
  "thwackability": 0.5252314374563855,
  "totalFingers": 13,
  "tournamentTeamId": null,
  "tragicness": 0.009284755063449545,
  "unthwackability": 0.4309509008937728,
  "watchfulness": 0.7216626572160306,
  "weekAttr": []
}