{
  "anticapitalism": 0.8135750345684183,
  "armor": "",
  "baseThirst": 0.20291323234021447,
  "baserunningRating": 0.5750035345796484,
  "bat": "",
  "blood": 8,
  "buoyancy": 0.8235795008815631,
  "chasiness": 0.8702371745692806,
  "cinnamon": 0.6738367415258026,
  "coffee": 12,
  "coldness": 0.3730183168043371,
  "continuation": 0.23653632102575076,
  "deceased": false,
  "defenseRating": 1.0026841355683451,
  "divinity": 0.31135781250538747,
  "eDensity": 31.538709725267413,
  "evolution": 0,
  "fate": 36,
  "gameAttr": [],
  "groundFriction": 0.9514284592395008,
  "hitStreak": 0,
  "hittingRating": 0.5759701962868585,
  "id": "d6c69d2d-9344-4b19-85a4-6cfcbaead5d2",
  "indulgence": 0.36363163969004286,
  "laserlikeness": 0.7503982747083743,
  "leagueTeamId": "adc5b394-8f76-416d-9ce9-813706877b84",
  "martyrdom": 0.6340826824597724,
  "moxie": 1.1929672594723284,
  "musclitude": 1.0784463960766766,
  "name": "Joshua Watson",
  "omniscience": 0.998806431270556,
  "overpowerment": 0.6369704365915863,
  "patheticism": 0.05482023085790511,
  "peanutAllergy": false,
  "permAttr": [
    "ALTERNATE"
  ],
  "pitchingRating": 0.6375863800319214,
  "pressurization": 0.0744220782424665,
  "ritual": "Lucid dreaming",
  "ruthlessness": 0.3869099433191844,
  "seasAttr": [],
  "shakespearianism": 0.6027197651026835,
  "soul": 6,
  "state": {},
  "suppression": 1.027935540759051,
  "tenaciousness": 1.1561588671367624,
  "thwackability": 0.6509332838426202,
  "totalFingers": 11,
  "tournamentTeamId": null,
  "tragicness": 0.001,
  "unthwackability": 1.1564976967659808,
  "watchfulness": 1.0879489125353343,
  "weekAttr": []
}