{
  "anticapitalism": 1.2479512580741212,
  "baseThirst": 0.29435227779344475,
  "baserunningRating": 0.8618533709738091,
  "blood": 11,
  "buoyancy": 0.7317846701056301,
  "chasiness": 0.5784448591766415,
  "cinnamon": 0.6321899392436022,
  "coffee": 2,
  "coldness": 1.0802175240274463,
  "continuation": 0.6957198476646729,
  "deceased": false,
  "defenseRating": 0.8301638693445936,
  "divinity": 1.0140114341485842,
  "eDensity": 39.95598484695229,
  "evolution": 0,
  "fate": 74,
  "gameAttr": [],
  "groundFriction": 0.3763953974813206,
  "hitStreak": 0,
  "hittingRating": 0.7820973697102842,
  "id": "d81ce662-07b6-4a73-baa4-acbbb41f9dc5",
  "indulgence": 1.1498151060079804,
  "itemAttr": [],
  "items": [
    {
      "baserunningRating": 0,
      "defenseRating": 0,
      "durability": 1,
      "forger": null,
      "forgerName": null,
      "health": 1,
      "hittingRating": 0.04069286286776286,
      "id": "4db146f8-c0b2-49f1-9a96-7ab9d14ff238",
      "name": "Bat",
      "pitchingRating": 0,
      "postPrefix": null,
      "prePrefix": null,
      "prefixes": null,
      "root": {
        "adjustments": [
          {
            "stat": 2,
            "type": 1,
            "value": 0.13415276865304154
          }
        ],
        "name": "Bat"
      },
      "suffix": null
    }
  ],
  "laserlikeness": 1.2060128843414395,
  "leagueTeamId": "878c1bf6-0d21-4659-bfee-916c8314d69c",
  "martyrdom": 0.6605674386588677,
  "moxie": 0.5836908938362941,
  "musclitude": 0.3006656628143832,
  "name": "Yummy Elliott",
  "omniscience": 0.5285068927007722,
  "overpowerment": 1.2527513215596229,
  "patheticism": 0.6958017195437436,
  "peanutAllergy": false,
  "permAttr": [],
  "pitchingRating": 1.0679066735727143,
  "pressurization": 0.3557395475255112,
  "ritual": "Comics",
  "ruthlessness": 1.2639355263160457,
  "seasAttr": [],
  "shakespearianism": 0.7462688474700152,
  "soul": 8,
  "state": {},
  "suppression": 1.066323805702537,
  "tenaciousness": 0.8513650550608707,
  "thwackability": 0.8611296208061313,
  "totalFingers": 12,
  "tournamentTeamId": null,
  "tragicness": 0.001,
  "unthwackability": 0.9334102805629,
  "watchfulness": 1.0637651020950072,
  "weekAttr": []
}