{
  "blessings": [
    {
      "description": "A random player on your team becomes BIG. Increased Power, Max Vibe. Decreased Baserunning.",
      "id": "item_mushroom",
      "subheader": "Brought to you by @HoloVista@https://apps.apple.com/us/app/holovista/id1474114304",
      "title": "Eat me, Drink me",
      "type": 61,
      "value": 1
    },
    {
      "description": "Zero to hero. The worst player on your team will earn 5x payouts for Idol Pendants.",
      "id": "worst_player_big_payouts",
      "subheader": "Brought to you by@the garages@https://thegarages.bandcamp.com",
      "title": "Credit to the Team",
      "type": 112,
      "value": 1
    },
    {
      "description": "They'll never see it coming. Maximize a random Pitcher in your Shadows.",
      "id": "maximize_random_shadow_pitcher",
      "subheader": "Brought to you by @It Came From A Basement Podcast@http://itcamefromabasement.com/blaseball",
      "title": "Secret Weapon",
      "type": 120,
      "value": 1
    },
    {
      "description": "Steal a Hitter from another Team's Shadows.",
      "id": "steal_random_team_best_bench",
      "title": "Grab and Smash",
      "type": 102,
      "value": 1
    },
    {
      "description": "Send your 2 Worst Pitchers to the Shadows and call up your First 2 Relievers.",
      "id": "send_worst_pitchers_to_shadows",
      "title": "Out of Sight",
      "type": 118,
      "value": 2
    },
    {
      "description": "Send your Worst 3 Hitters to the Shadows and call up the first 3 Shadows Hitters",
      "id": "send_worst_hitters_to_shadows",
      "title": "Disappearing Acts",
      "type": 119,
      "value": 3
    },
    {
      "description": "Give your Team Love Blood Type.",
      "id": "team_love_blood_type",
      "title": "Feel the Love",
      "type": 116,
      "value": 1
    },
    {
      "description": "Help yourselves. A player on each team in your Division gets Spicy.",
      "id": "mod_division_spicy",
      "title": "Hot Sauce Bar",
      "type": 115,
      "value": 1
    },
    {
      "description": "Give all of the teams not in your Division the Fifth Base.",
      "id": "mod_non_division_fifth_base",
      "title": "Fifth Base Bubble",
      "type": 109,
      "value": 1
    },
    {
      "description": "Give all of the teams not in your Division Targeted Shame.",
      "id": "mod_non_division_targeted_shame",
      "title": "The Shame Bubble",
      "type": 86,
      "value": 1
    },
    {
      "description": "Improve your team's pitching by 10%. The last place team in the opposite subleague also gets +10% team pitching.",
      "id": "shared_team_pitching",
      "title": "Tag Team Pitching",
      "type": 111,
      "value": 0.1
    },
    {
      "description": "Improve your team's hitting by 10%. The last place team in the opposite subleague also gets +10% team hitting.",
      "id": "shared_team_hitting",
      "title": "Tag Team Hitting",
      "type": 110,
      "value": 0.1
    },
    {
      "description": "Incinerate the Most Idolized Player on your Team.",
      "id": "incinerate_most_idolized",
      "title": "Kill Your Darling",
      "type": 114,
      "value": 1
    },
    {
      "description": "Shed it. Incinerate the Worst Player on Your Team.",
      "id": "incinerate_worst_player",
      "title": "Dead Weight",
      "type": 113,
      "value": 1
    },
    {
      "description": "A warm welcome. Incinerate the Least Idolized Player on Your Team.",
      "id": "incinerate_least_idolized",
      "title": "New Kid",
      "type": 103,
      "value": 1
    },
    {
      "description": "Feed the Hall Monitor. Fans of your team receive a big boatload of peanuts.",
      "id": "boatload_of_peanuts",
      "title": "Boatload of Tiny Eggs",
      "type": 104,
      "value": 10000
    },
    {
      "description": "Recruit a rookie to be an extra player in your lineup.",
      "id": "add_new_player_lineup",
      "title": "New Recruit",
      "type": 94,
      "value": 1
    },
    {
      "description": "Remove the worst player from your lineup. Your lineup is now shorter.",
      "id": "remove_worst_lineup",
      "title": "Downsizing",
      "type": 95,
      "value": 1
    },
    {
      "description": "Item. Max Out Defense for a random player on your team.",
      "id": "random_player_max_defense",
      "title": "Fishing Net",
      "type": 117,
      "value": 1
    },
    {
      "description": "Keep your enemies closer. Improve your entire division by 2%.",
      "id": "division_improve_overall",
      "title": "Mutually Arising",
      "type": 73,
      "value": 0.02
    }
  ],
  "decrees": [
    {
      "description": "Forecast: Eclipse",
      "id": "forecast_eclipse",
      "title": " ",
      "type": 37
    },
    {
      "description": "Forecast: Peanuts",
      "id": "forecast_peanuts",
      "title": " ",
      "type": 39
    },
    {
      "description": "Forecast: Birds",
      "id": "forecast_birds",
      "title": " ",
      "type": 34
    },
    {
      "description": "Forecast: Feedback",
      "id": "forecast_feedback",
      "title": " ",
      "type": 35
    },
    {
      "description": "Forecast: Reverb",
      "id": "forecast_reverb",
      "title": " ",
      "type": 38
    },
    {
      "description": "Forecast: Blooddrain",
      "id": "forecast_blooddrain",
      "title": " ",
      "type": 36
    }
  ],
  "decreesToPass": 3
}